totalspineseg/__init__.py
totalspineseg/inference.py
totalspineseg/init_inference.py
totalspineseg/models/__init__.py
totalspineseg/utils/augment.py
totalspineseg/utils/average4d.py
totalspineseg/utils/cpdir.py
totalspineseg/utils/crop_image2seg.py
totalspineseg/utils/extract_alternate.py
totalspineseg/utils/extract_levels.py
totalspineseg/utils/extract_soft.py
totalspineseg/utils/fill_canal.py
totalspineseg/utils/install_weights.py
totalspineseg/utils/iterative_label.py
totalspineseg/utils/largest_component.py
totalspineseg/utils/map_labels.py
totalspineseg/utils/predict_nnunet.py
totalspineseg/utils/preview_jpg.py
totalspineseg/utils/reorient_canonical.py
totalspineseg/utils/resample.py
totalspineseg/utils/transform_seg2image.py
totalspineseg/utils/utils.py
totalspineseg-20251021.dist-info/licenses/LICENSE
totalspineseg-20251021.dist-info/METADATA
totalspineseg-20251021.dist-info/WHEEL
totalspineseg-20251021.dist-info/entry_points.txt
totalspineseg-20251021.dist-info/top_level.txt
totalspineseg-20251021.dist-info/RECORD
