Metadata-Version: 2.4
Name: totalspineseg
Version: 20251021
Summary: TotalSpineSeg is a tool for automatic instance segmentation and labeling of all vertebrae, intervertebral discs (IVDs), spinal cord, and spinal canal in MRI images.
Author: Anat Achiron, Julien Cohen-Adad
Author-email: Yehuda Warszawer <yehuda.warszawer@sheba.health.gov.il>, Nathan Molinier <nathan.molinier@polymtl.ca>
Project-URL: homepage, https://github.com/neuropoly/totalspineseg
Project-URL: repository, https://github.com/neuropoly/totalspineseg
Project-URL: Dataset101_TotalSpineSeg_step1, https://github.com/neuropoly/totalspineseg/releases/download/r20241115/Dataset101_TotalSpineSeg_step1_r20241115.zip
Project-URL: Dataset102_TotalSpineSeg_step2, https://github.com/neuropoly/totalspineseg/releases/download/r20241115/Dataset102_TotalSpineSeg_step2_r20241115.zip
Keywords: deep learning,image segmentation,semantic segmentation,medical image analysis,medical image segmentation,nnU-Net,nnunet,mri,spine,ivd,intervertebral disc,spinal cord
Classifier: Development Status :: 5 - Production/Stable
Classifier: Intended Audience :: Science/Research
Classifier: Programming Language :: Python :: 3
Classifier: Topic :: Scientific/Engineering :: Artificial Intelligence
Classifier: Topic :: Scientific/Engineering :: Image Recognition
Classifier: Topic :: Scientific/Engineering :: Medical Science Apps.
Requires-Python: >=3.10
License-File: LICENSE
Requires-Dist: tqdm
Requires-Dist: numpy<2
Requires-Dist: nibabel
Requires-Dist: gryds
Requires-Dist: torchio
Requires-Dist: scipy
Requires-Dist: pillow
Requires-Dist: nilearn
Requires-Dist: SimpleITK
Requires-Dist: psutil
Requires-Dist: blosc2<3.9.0
Provides-Extra: nnunetv2
Requires-Dist: nnunetv2<=2.4.2; extra == "nnunetv2"
Provides-Extra: neuropoly
Requires-Dist: nnunetv2-neuropoly; extra == "neuropoly"
Dynamic: license-file
